src/__init__.py
src/args.py
src/constants.py
src/main.py
src/util.py
src/validation.py
json_clip-1.0.2.dist-info/LICENSE.txt
json_clip-1.0.2.dist-info/METADATA
json_clip-1.0.2.dist-info/WHEEL
json_clip-1.0.2.dist-info/entry_points.txt
json_clip-1.0.2.dist-info/top_level.txt
json_clip-1.0.2.dist-info/RECORD
