Metadata-Version: 2.1
Name: json-clip
Version: 1.0.2
Summary: A command-line utility for efficient management of text snippets and keys, designed to simplify the storage, retrieval, and organization of frequently used text and commands
Home-page: https://github.com/Siva-0310/clip
Author: Chadalawada Siva Bala Krishna Chowdary
Author-email: sivachadalawada1923@gmail.com
Classifier: Programming Language :: Python :: 3
Classifier: License :: OSI Approved :: MIT License
Classifier: Operating System :: OS Independent
License-File: LICENSE.txt
